{
  "title": "Slik finner du frem / Asker Fotball",
  "url": "https://askerfotball.no/om-stadion/slik-finner-du-frem",
  "breadcrumbs": [],
  "content": "Slik finner du frem / Asker Fotball\n••\n••\n•••\n•• •Slik finner du frem til Føyka[Forsiden](https://askerfotball.no/)\n/\n/-->**Parkering:&nbsp;**Du kan parkere mot avgift nedenfor stadion. Husk synlig billett i vinduet.&nbsp;Annonse:### Populære søk[PROFIL](https://askerfotball.no/pwa)[REDIGER PROFIL](https://askerfotball.no/pwa?edit=true)EPostMobilnummerFødselsdatoAdressePostnr.PoststedKjønn#### PushmeldingerSpesielle utvalgte nyheterAlle nyheterKamphendelser#### Kommunikasjon og SamtykkerREDIGER SAMTYKKERNyheterLagTerminlisteResultaterOm stadionOm klubbenAskerfotballens historieMarkedSamfunnButikkFøyka OBOS-campOBOS-AkademietFordelsprogramPUSH-VARSLINGERXX## HeaderContentXHeaderContentDenne nettsiden bruker cookies – se nærmere i vår cookie- og personvernerklæring.[Ok](#cookie-line-accept)[Les mer her](https://www.obos-ligaen.no/personvern)",
  "published_at": null,
  "lang": "no",
  "meta": {
    "description": "Slik finner du frem til Føyka"
  },
  "word_count": 59,
  "parsed_at": "2025-10-16T14:10:43.633Z"
}